charlotte_db/Matrix_def.py
charlotte_db/__init__.py
charlotte_db/charlotte_DB_SDK.py
charlotte_db-0.8.4.dist-info/DESCRIPTION.rst
charlotte_db-0.8.4.dist-info/METADATA
charlotte_db-0.8.4.dist-info/RECORD
charlotte_db-0.8.4.dist-info/WHEEL
charlotte_db-0.8.4.dist-info/metadata.json
charlotte_db-0.8.4.dist-info/top_level.txt
