Metadata-Version: 2.0
Name: charlotte-db
Version: 0.8.4
Summary: A lighting fast SDK for a lighting fast DB
Home-page: https://github.com/Danlobaton/flash-Charlotte-docs
Author: Daniel A. Lobaton
Author-email: dlobaton2@gmail.com
License: MIT
Keywords: SDK
Platform: UNKNOWN
Classifier: Development Status :: 3 - Alpha
Classifier: Intended Audience :: Developers
Classifier: License :: OSI Approved :: MIT License
Requires-Dist: numpy (>=1.12.1)
Requires-Dist: tensorflow (>=1.1.0)
